[
  {
    "question": "A particle of mass $m$ and charge $q$ moves in a uniform magnetic field $\\vec{B} = 2B\\hat{k}$. The Lagrangian is given by $L = \\frac{m}{2}(\\dot{x}^2 + \\dot{y}^2 + \\dot{z}^2) + qB(x\\dot{y} - y\\dot{x})$. Which of the following defines the conjugate momentum $p_x$ and the corresponding Hamilton's equation for $\\dot{x}$?",
    "options": [
      {
        "label": 1,
        "value": "$p_x = m\\dot{x} + qBy$ and $\\dot{x} = \\frac{1}{m}(p_x - qBy)$"
      },
      {
        "label": 2,
        "value": "$p_x = m\\dot{x} - qBy$ and $\\dot{x} = \\frac{1}{m}(p_x + qBy)$"
      },
      {
        "label": 3,
        "value": "$p_x = m\\dot{x} - qBy$ and $\\dot{x} = \\frac{1}{m}(p_x - qBy)$"
      },
      {
        "label": 4,
        "value": "$p_x = m\\dot{x} + qBy$ and $\\dot{x} = \\frac{1}{m}(p_x + qBy)$"
      }
    ],
    "answer_label": 2,
    "topic": "Lagrangian Dynamics & Conjugate Momenta",
    "explanation": "The conjugate momentum is $p_x = \\frac{\\partial L}{\\partial \\dot{x}} = m\\dot{x} - qBy$. Rearranging for the velocity gives $\\dot{x} = \\frac{1}{m}(p_x + qBy)$. This matches option 2.",
    "image_path": null
  },
  {
    "question": "Consider a second-rank symmetric tensor $A^{\\mu\\nu}$ in a frame $S$. In this frame, the diagonal components are $A^{tt} = P$ and $A^{xx} = Q$, while off-diagonal components are zero. If $S'$ moves with velocity $v$ along the $x$-axis relative to $S$, what is the expression for the transformed component $A'^{tt}$?",
    "options": [
      {
        "label": 1,
        "value": "$A'^{tt} = \\gamma^2(P + v^2 Q)$"
      },
      {
        "label": 2,
        "value": "$A'^{tt} = \\gamma^2(v^2 P + Q)$"
      },
      {
        "label": 3,
        "value": "$A'^{tt} = \\gamma(P - vQ)$"
      },
      {
        "label": 4,
        "value": "$A'^{tt} = \\gamma^2(P - v^2 Q)$"
      }
    ],
    "answer_label": 1,
    "topic": "Lorentz Transformations of Tensors",
    "explanation": "Using the transformation $A'^{\\mu\\nu} = \\Lambda^\\mu_\\alpha \\Lambda^\nu_\\beta A^{\\alpha\\beta}$, we have $A'^{tt} = (\\Lambda^t_t)^2 A^{tt} + (\\Lambda^t_x)^2 A^{xx}$. Since $\\Lambda^t_t = \\gamma$ and $\\Lambda^t_x = -\\gamma v$, we get $A'^{tt} = \\gamma^2 P + (-\\gamma v)^2 Q = \\gamma^2(P + v^2 Q)$.",
    "image_path": null
  },
  {
    "question": "A bead is constrained to move on a frictionless horizontal rod that is moving vertically upward with a constant speed $v_0$. If the Hamiltonian of the system is $H$, which of the following statements is true regarding energy and conservation?",
    "options": [
      {
        "label": 1,
        "value": "$H$ is the total energy and is conserved because the rod moves at constant speed."
      },
      {
        "label": 2,
        "value": "$H$ is not the total energy, but it is conserved because the Lagrangian is not explicitly time-dependent."
      },
      {
        "label": 3,
        "value": "$H$ is the total energy but is not conserved because gravity does work."
      },
      {
        "label": 4,
        "value": "$H$ is not the total energy and is not conserved because the constraint is time-dependent."
      }
    ],
    "answer_label": 4,
    "topic": "Hamiltonian Dynamics & Conservation Laws",
    "explanation": "Because the vertical position $z = v_0 t$ is a time-dependent constraint (rheonomous), the Hamiltonian $H$ is not equal to the total energy $T+V$. Furthermore, since the constraint depends on time, the energy is not conserved as the external agent moving the rod does work.",
    "image_path": null
  },
  {
    "question": "A canonical transformation is defined by $Q = \\frac{1}{p}$ and $P = q p^2$. What is the Poisson bracket $\\{Q, P\\}_{q,p}$ for this transformation to be valid?",
    "options": [
      {
        "label": 1,
        "value": "0"
      },
      {
        "label": 2,
        "value": "1"
      },
      {
        "label": 3,
        "value": "$p$"
      },
      {
        "label": 4,
        "value": "$q/p$"
      }
    ],
    "answer_label": 2,
    "topic": "Canonical Transformations",
    "explanation": "For a transformation to be canonical, the fundamental Poisson bracket $\\{Q, P\\}_{q,p}$ must equal 1. Calculating: $\\frac{\\partial Q}{\\partial q}\\frac{\\partial P}{\\partial p} - \\frac{\\partial Q}{\\partial p}\\frac{\\partial P}{\\partial q} = (0)(2qp) - (-\\frac{1}{p^2})(p^2) = 0 + 1 = 1$.",
    "image_path": null
  },
  {
    "question": "An object exhibits $n$-fold rotational symmetry if it is invariant under a rotation of $2\\pi/n$. Which of the following shapes necessarily possesses 4-fold rotational symmetry about its center in a 2D plane?",
    "options": [
      {
        "label": 1,
        "value": "An equilateral triangle"
      },
      {
        "label": 2,
        "value": "A regular hexagon"
      },
      {
        "label": 3,
        "value": "A square"
      },
      {
        "label": 4,
        "value": "A non-square rhombus"
      }
    ],
    "answer_label": 3,
    "topic": "Rotational Symmetry",
    "explanation": "A square is invariant under rotations of $90^\\circ$ ($2\\pi/4$), thus it has 4-fold symmetry. A triangle has 3-fold, a hexagon 6-fold, and a rhombus generally 2-fold.",
    "image_path": null
  },
  {
    "question": "For a two-dimensional hexagonal lattice with lattice constant $a$, the area of the primitive unit cell is $\\frac{\\sqrt{3}}{2}a^2$. Given there is one atom per primitive cell, what is the atomic density?",
    "options": [
      {
        "label": 1,
        "value": "$\\frac{1}{\\sqrt{3}a^2}$"
      },
      {
        "label": 2,
        "value": "$\\frac{2}{\\sqrt{3}a^2}$"
      },
      {
        "label": 3,
        "value": "$\\frac{4}{3\\sqrt{3}a^2}$"
      },
      {
        "label": 4,
        "value": "$\\frac{1}{3\\sqrt{3}a^2}$"
      }
    ],
    "answer_label": 2,
    "topic": "Crystal Symmetry & Lattice Properties",
    "explanation": "Atomic density $n = \\frac{N}{A}$. For a primitive cell, $N=1$. $A = \\frac{\\sqrt{3}}{2}a^2$. Thus $n = \\frac{1}{\\sqrt{3}a^2/2} = \\frac{2}{\\sqrt{3}a^2}$.",
    "image_path": null
  },
  {
    "question": "If a Lagrangian $L(q, \\dot{q})$ is invariant under the continuous spatial translation $q \to q + \\epsilon$, which quantity is conserved according to Noether's theorem?",
    "options": [
      {
        "label": 1,
        "value": "Kinetic Energy"
      },
      {
        "label": 2,
        "value": "Angular Momentum"
      },
      {
        "label": 3,
        "value": "Linear Momentum"
      },
      {
        "label": 4,
        "value": "Hamiltonian"
      }
    ],
    "answer_label": 3,
    "topic": "Noether's Theorem",
    "explanation": "Noether's theorem states that every continuous symmetry of the action corresponds to a conservation law. Spatial translation symmetry corresponds to the conservation of linear momentum.",
    "image_path": null
  },
  {
    "question": "A particle moves in a potential $V(r)$ that depends only on the distance from the origin. Which symmetry does this system possess, and what is the conserved quantity?",
    "options": [
      {
        "label": 1,
        "value": "Translational symmetry; Linear momentum"
      },
      {
        "label": 2,
        "value": "Rotational symmetry; Angular momentum"
      },
      {
        "label": 3,
        "value": "Time symmetry; Potential energy"
      },
      {
        "label": 4,
        "value": "Reflection symmetry; Parity"
      }
    ],
    "answer_label": 2,
    "topic": "Symmetry & Conservation Laws",
    "explanation": "A potential $V(r)$ is invariant under rotations about the origin. Rotational symmetry leads to the conservation of angular momentum $\\vec{L}$.",
    "image_path": null
  },
  {
    "question": "Consider the Lagrangian $L = \\frac{1}{2}m(\\dot{r}^2 + r^2 \\dot{\\theta}^2) - V(r)$. The coordinate $\\theta$ is cyclic. What is the constant of motion associated with this cyclic coordinate?",
    "options": [
      {
        "label": 1,
        "value": "$mr\\dot{\\theta}$"
      },
      {
        "label": 2,
        "value": "$mr^2\\dot{\\theta}$"
      },
      {
        "label": 3,
        "value": "$m\\dot{r}$"
      },
      {
        "label": 4,
        "value": "$\\frac{1}{2}mr^2\\dot{\\theta}^2$"
      }
    ],
    "answer_label": 2,
    "topic": "Cyclic Coordinates",
    "explanation": "A coordinate is cyclic if it does not appear in the Lagrangian. The conjugate momentum $p_\\theta = \\frac{\\partial L}{\\partial \\dot{\\theta}} = mr^2\\dot{\\theta}$ is then conserved.",
    "image_path": null
  },
  {
    "question": "In quantum mechanics, if the Hamiltonian $H$ commutes with the parity operator $P$ ($[H, P] = 0$), what can be said about the energy eigenstates?",
    "options": [
      {
        "label": 1,
        "value": "They must all have zero eigenvalue."
      },
      {
        "label": 2,
        "value": "They can be chosen to be simultaneous eigenstates of $P$ with eigenvalues $\\pm 1$."
      },
      {
        "label": 3,
        "value": "They are all non-degenerate."
      },
      {
        "label": 4,
        "value": "They must be invariant under time reversal."
      }
    ],
    "answer_label": 2,
    "topic": "Discrete Symmetries in QM",
    "explanation": "If an operator commutes with the Hamiltonian, they share a common set of eigenstates. Since $P^2 = I$, the eigenvalues of the parity operator are $\\pm 1$ (even or odd parity).",
    "image_path": null
  },
  {
    "question": "Under a Time Reversal ($T$) transformation in classical mechanics, which of the following quantities changes sign?",
    "options": [
      {
        "label": 1,
        "value": "Position $\\vec{r}$"
      },
      {
        "label": 2,
        "value": "Acceleration $\\vec{a}$"
      },
      {
        "label": 3,
        "value": "Momentum $\\vec{p}$"
      },
      {
        "label": 4,
        "value": "Kinetic Energy $T$"
      }
    ],
    "answer_label": 3,
    "topic": "Time Reversal Symmetry",
    "explanation": "Under $t \to -t$, $\\vec{r}$ remains unchanged, but velocity $\\vec{v} = d\\vec{r}/dt$ changes sign. Consequently, momentum $\\vec{p} = m\\vec{v}$ changes sign. Acceleration ($d^2\\vec{r}/dt^2$) and Kinetic energy ($\\propto v^2$) remain unchanged.",
    "image_path": null
  },
  {
    "question": "The Lagrangian of a system is $L = \\frac{1}{2}\\dot{q}^2 - \\frac{1}{2}q^2$. This system is invariant under the transformation $q(t) \to q(t) + \\delta q(t)$. For what $\\delta q(t)$ is the action invariant if we consider the symmetry of a simple harmonic oscillator?",
    "options": [
      {
        "label": 1,
        "value": "A constant displacement $\\epsilon$"
      },
      {
        "label": 2,
        "value": "A transformation $q \to q e^{\\epsilon}$"
      },
      {
        "label": 3,
        "value": "It is not invariant under spatial translations."
      },
      {
        "label": 4,
        "value": "A transformation $q \to q + \\epsilon \\dot{q}$"
      }
    ],
    "answer_label": 3,
    "topic": "Noether's Theorem Application",
    "explanation": "For the SHO potential $V(q) = \\frac{1}{2}q^2$, a translation $q \to q + \\epsilon$ changes the potential to $\\frac{1}{2}(q+\\epsilon)^2$, which is not equal to $\\frac{1}{2}q^2$. Thus, the system does not have translation symmetry, and linear momentum is not conserved.",
    "image_path": null
  },
  {
    "question": "Which of the following describes the transformation of the electromagnetic vector potential $\\vec{A}$ and scalar potential $\\phi$ under a gauge transformation that leaves $\\vec{E}$ and $\\vec{B}$ invariant?",
    "options": [
      {
        "label": 1,
        "value": "$\\vec{A} \to \\vec{A} + \\nabla \\Lambda, \\phi \to \\phi - \\frac{\\partial \\Lambda}{\\partial t}$"
      },
      {
        "label": 2,
        "value": "$\\vec{A} \to \\vec{A} - \\nabla \\Lambda, \\phi \to \\phi + \\frac{\\partial \\Lambda}{\\partial t}$"
      },
      {
        "label": 3,
        "value": "$\\vec{A} \to \\Lambda \\vec{A}, \\phi \to \\Lambda \\phi$"
      },
      {
        "label": 4,
        "value": "$\\vec{A} \to \\vec{A} + \\nabla \\times \\Lambda, \\phi \to \\phi$"
      }
    ],
    "answer_label": 1,
    "topic": "Gauge Symmetry",
    "explanation": "Standard gauge transformations in electrodynamics are defined by adding the gradient of a scalar field to $\\vec{A}$ and subtracting the time derivative from $\\phi$.",
    "image_path": null
  },
  {
    "question": "A system is described by the Hamiltonian $H = \\frac{p^2}{2m} + \\alpha q p$. Is the momentum $p$ conserved?",
    "options": [
      {
        "label": 1,
        "value": "Yes, because $H$ is quadratic in $p$."
      },
      {
        "label": 2,
        "value": "No, because $q$ is not a cyclic coordinate in the Hamiltonian."
      },
      {
        "label": 3,
        "value": "Yes, because there are no external forces."
      },
      {
        "label": 4,
        "value": "No, because the Hamiltonian depends on time."
      }
    ],
    "answer_label": 2,
    "topic": "Conservation from Hamiltonian",
    "explanation": "$\\dot{p} = -\\frac{\\partial H}{\\partial q} = -\\alpha p$. Since $\\frac{\\partial H}{\\partial q} \\neq 0$ (unless $p=0$), the coordinate $q$ is not cyclic, and its conjugate momentum $p$ is not conserved.",
    "image_path": null
  },
  {
    "question": "If the Lagrangian $L(q, \\dot{q}, t)$ is multiplied by a constant factor $k$, how do the equations of motion change?",
    "options": [
      {
        "label": 1,
        "value": "The equations of motion are scaled by $k$."
      },
      {
        "label": 2,
        "value": "The equations of motion remain unchanged."
      },
      {
        "label": 3,
        "value": "The acceleration is increased by a factor of $k$."
      },
      {
        "label": 4,
        "value": "The system becomes non-conservative."
      }
    ],
    "answer_label": 2,
    "topic": "Symmetry of the Action",
    "explanation": "The Euler-Lagrange equations $\\frac{d}{dt}(\\frac{\\partial L}{\\partial \\dot{q}}) - \\frac{\\partial L}{\\partial q} = 0$ are linear in $L$. Multiplying $L$ by a constant $k$ results in $k[\\dots] = 0$, which yields the same roots/physics.",
    "image_path": null
  },
  {
    "question": "A crystal has primitive vectors $\\vec{a}_1 = a\\hat{i}$, $\\vec{a}_2 = a\\hat{j}$, $\\vec{a}_3 = \\frac{a}{2}(\\hat{i} + \\hat{j} + \\hat{k})$. What is the volume of the primitive unit cell?",
    "options": [
      {
        "label": 1,
        "value": "$a^3$"
      },
      {
        "label": 2,
        "value": "$a^3/2$"
      },
      {
        "label": 3,
        "value": "$a^3/4$"
      },
      {
        "label": 4,
        "value": "$2a^3$"
      }
    ],
    "answer_label": 2,
    "topic": "Lattice Symmetry & Geometry",
    "explanation": "The volume $V = |\\vec{a}_1 \\cdot (\\vec{a}_2 \\times \\vec{a}_3)|$. $\\vec{a}_2 \\times \\vec{a}_3 = a\\hat{j} \\times \\frac{a}{2}(\\hat{i} + \\hat{j} + \\hat{k}) = \\frac{a^2}{2}(-\\hat{k} + 0 + \\hat{i})$. Then $\\vec{a}_1 \\cdot \\frac{a^2}{2}(\\hat{i} - \\hat{k}) = (a\\hat{i}) \\cdot \\frac{a^2}{2}(\\hat{i} - \\hat{k}) = a^3/2$.",
    "image_path": null
  },
  {
    "question": "Consider the transformation of coordinates in relativity. If a tensor $A^{\\mu\\nu}$ is anti-symmetric ($A^{\\mu\\nu} = -A^{\\nu\\mu}$) in one frame, what is its property in a Lorentz-transformed frame?",
    "options": [
      {
        "label": 1,
        "value": "It becomes symmetric."
      },
      {
        "label": 2,
        "value": "It remains anti-symmetric."
      },
      {
        "label": 3,
        "value": "All components become zero."
      },
      {
        "label": 4,
        "value": "Only the diagonal components remain anti-symmetric."
      }
    ],
    "answer_label": 2,
    "topic": "Relativistic Symmetries",
    "explanation": "Symmetry and anti-symmetry are tensor properties that are invariant under any linear coordinate transformation, including Lorentz transformations.",
    "image_path": null
  },
  {
    "question": "In a 1D system, the Lagrangian is $L = \\frac{1}{2}m\\dot{x}^2 - V(x)$. If $V(x) = V(-x)$, the system is invariant under space inversion (Parity). What is the conserved quantity in quantum mechanics associated with this?",
    "options": [
      {
        "label": 1,
        "value": "Linear momentum"
      },
      {
        "label": 2,
        "value": "Parity eigenvalue"
      },
      {
        "label": 3,
        "value": "Angular momentum"
      },
      {
        "label": 4,
        "value": "Energy only"
      }
    ],
    "answer_label": 2,
    "topic": "Parity Conservation",
    "explanation": "For a symmetric potential, the Parity operator $P$ commutes with the Hamiltonian $[H, P] = 0$. Thus, parity is a conserved quantum number (the eigenvalue of $P$).",
    "image_path": null
  },
  {
    "question": "If the Lagrangian is explicitly dependent on time ($L = L(q, \\dot{q}, t)$), which of the following is generally true?",
    "options": [
      {
        "label": 1,
        "value": "Linear momentum is conserved."
      },
      {
        "label": 2,
        "value": "The Hamiltonian $H$ is a constant of motion."
      },
      {
        "label": 3,
        "value": "The energy of the system is not conserved."
      },
      {
        "label": 4,
        "value": "The system must be in an inertial frame."
      }
    ],
    "answer_label": 3,
    "topic": "Time Translation Symmetry",
    "explanation": "Conservation of energy is a result of time-translation symmetry. If $L$ depends explicitly on $t$, this symmetry is broken, and $dH/dt = -\\partial L/\\partial t \\neq 0$.",
    "image_path": null
  },
  {
    "question": "A transformation $(q, p) \to (Q, P)$ is canonical if it preserves the form of Hamilton's equations. This is equivalent to saying the transformation is:",
    "options": [
      {
        "label": 1,
        "value": "Symplectic"
      },
      {
        "label": 2,
        "value": "Orthogonal"
      },
      {
        "label": 3,
        "value": "Unitary"
      },
      {
        "label": 4,
        "value": "Isometric"
      }
    ],
    "answer_label": 1,
    "topic": "Canonical Transformations",
    "explanation": "Canonical transformations are those that preserve the symplectic structure of phase space, often represented by the Jacobian matrix satisfying $M^T J M = J$.",
    "image_path": null
  }
]